riptide_db_mysql/__init__.py
riptide_db_mysql/mysql.py
riptide_db_mysql-0.9.1.dist-info/licenses/LICENSE
riptide_db_mysql-0.9.1.dist-info/METADATA
riptide_db_mysql-0.9.1.dist-info/WHEEL
riptide_db_mysql-0.9.1.dist-info/entry_points.txt
riptide_db_mysql-0.9.1.dist-info/top_level.txt
riptide_db_mysql-0.9.1.dist-info/RECORD
